[
  {
    "전과건수": 0,
    "imageUrl": "https://raw.githubusercontent.com/WhiteKiwi/law-maker/main/data/images/candidates/2441802-1.jpg",
    "id": "2441802-1",
    "재산": 451668,
    "생년월일": "19730105",
    "경력": "(현) 제21대 국회의원\n(전) 천안시 고문변호사",
    "학력": "한양대학교 법과대학 법학과 졸업",
    "직업": "국회의원",
    "성별": "남",
    "id_21th": "1128",
    "regionId": "2441802",
    "기호": 1,
    "군필여부": true,
    "news": [
      {
        "date": "Mon, 01 Apr 2024 12:12:00 +0900",
        "title": "[인터뷰] 이정문 \"기본 충실·초심 유지…100만 천안 도약 견인\"",
        "link": "http://www.newstnt.com/news/articleView.html?idxno=358687"
      },
      {
        "date": "Sun, 31 Mar 2024 05:20:00 +0900",
        "title": "교육공약 3인 3색…이정문·이창수·한정애 복안은 [천안병 TV토론]",
        "link": "https://n.news.naver.com/mnews/article/119/0002815283?sid=165"
      },
      {
        "date": "Fri, 29 Mar 2024 10:10:00 +0900",
        "title": "민주당 천안 문진석·이재관·이정문 \"정의의 철퇴\"",
        "link": "http://www.goodmorningcc.com/news/articleView.html?idxno=307201"
      },
      {
        "date": "Fri, 29 Mar 2024 09:06:00 +0900",
        "title": "국민변호인 이정문 총선 출정식 \"참된 일꾼에 맡겨달라\"",
        "link": "http://www.lawleader.co.kr/news/articleView.html?idxno=12772"
      },
      {
        "date": "Fri, 29 Mar 2024 09:04:00 +0900",
        "title": "더불어민주당 천안갑·을·병 문진석·이재관·이정문 후보 본격 선거운동 돌...",
        "link": "https://www.ccdailynews.com/news/articleView.html?idxno=2265389"
      }
    ],
    "정당": "더불어민주당",
    "이름": "이정문",
    "연도별_재산": [
      {
        "연도": 2020,
        "재산": 341925
      },
      {
        "연도": 2021,
        "재산": 475129
      },
      {
        "연도": 2022,
        "재산": 539052
      },
      {
        "연도": 2023,
        "재산": 451668
      }
    ],
    "huboid": "100152586",
    "전과ImgUrl": "https://raw.githubusercontent.com/WhiteKiwi/law-maker/main/data/images/jeon-gwa/2441802-1.jpg"
  },
  {
    "전과건수": 0,
    "imageUrl": "https://raw.githubusercontent.com/WhiteKiwi/law-maker/main/data/images/candidates/2441802-2.jpg",
    "id": "2441802-2",
    "재산": 526856,
    "생년월일": "19630105",
    "경력": "(전) 국민의힘 천안병 당협위원장\n(현) 국민의힘 중앙당 인권위원장",
    "학력": "단국대학교 국어국문학과 졸업",
    "직업": "정당인",
    "성별": "남",
    "regionId": "2441802",
    "기호": 2,
    "군필여부": true,
    "news": [
      {
        "date": "Tue, 02 Apr 2024 19:06:00 +0900",
        "title": "지지 호소하는 이창수 천안병 국민의힘 후보",
        "link": "https://n.news.naver.com/mnews/article/421/0007454014?sid=165"
      },
      {
        "date": "Tue, 02 Apr 2024 19:06:00 +0900",
        "title": "이창수 '천안은 기호 2번'",
        "link": "https://n.news.naver.com/mnews/article/421/0007454013?sid=165"
      },
      {
        "date": "Tue, 02 Apr 2024 14:12:00 +0900",
        "title": "[포토] 이창수 천안병 후보 \"3번 낙선한 이창수입니다\"",
        "link": "https://www.newdaily.co.kr/site/data/html/2024/04/02/2024040200205.html"
      },
      {
        "date": "Mon, 01 Apr 2024 20:38:00 +0900",
        "title": "국힘 천안병 이창수 · 아산을 전만권 \"GTX-A 노선 천안아산역 연장 추진\"",
        "link": "http://www.cctimes.kr/news/articleView.html?idxno=792436"
      },
      {
        "date": "Mon, 01 Apr 2024 19:17:00 +0900",
        "title": "4.10총선=국민의 힘 전만권(아산을), 이창수(천안 병) 후보 \"아산·천안 신 교...",
        "link": "http://www.dynews.co.kr/news/articleView.html?idxno=746272"
      }
    ],
    "정당": "국민의힘",
    "이름": "이창수",
    "연도별_재산": [
      {
        "연도": 2023,
        "재산": 526856
      }
    ],
    "huboid": "100151961",
    "전과ImgUrl": "https://raw.githubusercontent.com/WhiteKiwi/law-maker/main/data/images/jeon-gwa/2441802-2.jpg"
  },
  {
    "전과건수": 1,
    "imageUrl": "https://raw.githubusercontent.com/WhiteKiwi/law-maker/main/data/images/candidates/2441802-5.jpg",
    "id": "2441802-5",
    "재산": 161250,
    "생년월일": "19690610",
    "경력": "(현) 녹색정의당 충남도당 위원장\n(전) 제8회 전국동시지방선거 정의당 비례대표 충청남도의원 후보자",
    "학력": "천안여자고등학교 졸업",
    "직업": "자영업",
    "성별": "여",
    "regionId": "2441802",
    "기호": 5,
    "군필여부": false,
    "news": [
      {
        "date": "Sun, 31 Mar 2024 05:20:00 +0900",
        "title": "교육공약 3인 3색…이정문·이창수·한정애 복안은 [천안병 TV토론]",
        "link": "https://n.news.naver.com/mnews/article/119/0002815283?sid=165"
      },
      {
        "date": "Sat, 30 Mar 2024 09:20:00 +0900",
        "title": "녹색정의당 대표단 30일 천안병 한정애 후보 집중 유세 나서",
        "link": "https://www.ccdailynews.com/news/articleView.html?idxno=2265493"
      },
      {
        "date": "Sat, 23 Mar 2024 15:22:00 +0900",
        "title": "제22대 총선 '천안병' 누가 뛰나?...이정문·이창수·한정애·이성진 '4파전'",
        "link": "http://www.newstnt.com/news/articleView.html?idxno=355833"
      },
      {
        "date": "Fri, 22 Mar 2024 00:30:00 +0900",
        "title": "이정문·이창수·한정애, '젊은 천안'의 교육 이슈 주목 [천안·아산 토론회③...",
        "link": "https://n.news.naver.com/mnews/article/119/0002812160?sid=165"
      },
      {
        "date": "Wed, 20 Mar 2024 14:44:00 +0900",
        "title": "\"아직 기호도 몰라\" 녹색정의당 한정애 후보, 양당 꼼수정치 비판",
        "link": "https://n.news.naver.com/mnews/article/421/0007423954?sid=165"
      }
    ],
    "정당": "녹색정의당",
    "이름": "한정애",
    "연도별_재산": [
      {
        "연도": 2023,
        "재산": 161250
      }
    ],
    "huboid": "100152844",
    "전과ImgUrl": "https://raw.githubusercontent.com/WhiteKiwi/law-maker/main/data/images/jeon-gwa/2441802-5.jpg"
  },
  {
    "전과건수": 1,
    "imageUrl": "https://raw.githubusercontent.com/WhiteKiwi/law-maker/main/data/images/candidates/2441802-7.jpg",
    "id": "2441802-7",
    "재산": 1097672,
    "생년월일": "19790912",
    "경력": "(전) BBC 다큐멘터리 포토그래퍼\n(전) 국무조정실 충청남도 청년정책조정위원장",
    "학력": "문학사(심리학 전공)",
    "직업": "기업인",
    "성별": "남",
    "regionId": "2441802",
    "기호": 7,
    "군필여부": true,
    "news": [
      {
        "date": "Sun, 24 Mar 2024 15:24:00 +0900",
        "title": "천안병 이성진 \"정치 문턱 너무 좁아\"",
        "link": "http://www.goodmorningcc.com/news/articleView.html?idxno=306876"
      },
      {
        "date": "Sat, 23 Mar 2024 15:22:00 +0900",
        "title": "제22대 총선 '천안병' 누가 뛰나?...이정문·이창수·한정애·이성진 '4파전'",
        "link": "http://www.newstnt.com/news/articleView.html?idxno=355833"
      },
      {
        "date": "Thu, 21 Mar 2024 08:52:00 +0900",
        "title": "천안병 이성진 \"감옥 보내고, 욕하고…살림살이는?\"",
        "link": "http://www.goodmorningcc.com/news/articleView.html?idxno=306709"
      },
      {
        "date": "Wed, 20 Mar 2024 10:40:00 +0900",
        "title": "개혁신당 이성진 천안병 국회의원 후보, 기자회견 열고 출사표",
        "link": "https://www.newsfreezone.co.kr/news/articleView.html?idxno=555785"
      },
      {
        "date": "Tue, 19 Mar 2024 15:48:00 +0900",
        "title": "천안병 이성진 \"국민 아프게 한 정치 장벽 넘을 것\"",
        "link": "http://www.goodmorningcc.com/news/articleView.html?idxno=306600"
      }
    ],
    "정당": "개혁신당",
    "이름": "이성진",
    "연도별_재산": [
      {
        "연도": 2023,
        "재산": 1097672
      }
    ],
    "huboid": "100153037",
    "전과ImgUrl": "https://raw.githubusercontent.com/WhiteKiwi/law-maker/main/data/images/jeon-gwa/2441802-7.jpg"
  }
]
