[
  {
    "id": "2461801-1",
    "regionId": "2461801",
    "imageUrl": "http://info.nec.go.kr/photo_20240410/Gsg4618/Hb100151208/gicho/thumbnail.100151208.JPG?ver=1549179",
    "기호": 1,
    "이름": "박지원",
    "생년월일": "19420605",
    "정당": "더불어민주당",
    "성별": "남",
    "직업": "정치인",
    "학력": "단국대학교 상학과 졸업",
    "경력": "(전) 국가정보원 원장\n(전) 김대중 대통령비서실장",
    "재산": 2933069,
    "군필여부": true,
    "전과건수": 1
  },
  {
    "id": "2461801-2",
    "regionId": "2461801",
    "imageUrl": "http://info.nec.go.kr/photo_20240410/Gsg4618/Hb100151644/gicho/thumbnail.100151644.JPG?ver=1556276",
    "기호": 2,
    "이름": "곽봉근",
    "생년월일": "19450101",
    "정당": "국민의힘",
    "성별": "남",
    "직업": "정당인",
    "학력": "목포과학대학교 케어복지과 졸업",
    "경력": "(전) 윤석열 대통령후보 직능본부 부본부장\n(현) 국민의힘 국책자문위원회 고문",
    "재산": 10000,
    "군필여부": true,
    "전과건수": 4
  }
]