[
  {
    "id": "2471903-2",
    "regionId": "2471903",
    "imageUrl": "http://info.nec.go.kr/photo_20240410/Gsg4719/Hb100152784/gicho/thumbnail.100152784.JPG?ver=1673989",
    "기호": 2,
    "이름": "박형수",
    "생년월일": "19651020",
    "정당": "국민의힘",
    "성별": "남",
    "직업": "정당인(국회의원)",
    "학력": "서울대학교 법과대학 사법학과 졸업",
    "경력": "(현)제21대 국회의원\n(전)국민의힘 원내대변인",
    "재산": 2151582,
    "군필여부": true,
    "전과건수": 0
  },
  {
    "id": "2471903-7",
    "regionId": "2471903",
    "imageUrl": "http://info.nec.go.kr/photo_20240410/Gsg4719/Hb100151483/gicho/thumbnail.100151483.JPG?ver=1552218",
    "기호": 7,
    "이름": "심태성",
    "생년월일": "19850627",
    "정당": "무소속",
    "성별": "남",
    "직업": "상상수산 대표",
    "학력": "영산대학교 인도비즈니스학과 졸업",
    "경력": "(현)영덕대게랑 대표\n(현)상상수산 대표",
    "재산": 43729,
    "군필여부": true,
    "전과건수": 0
  }
]