{
  "연락처": "의원회관 821호 | 전화 02-784-5961 | 팩스 02-6788-6760",
  "당선횟수": 1,
  "본회의_출석률": 79.64,
  "소속위원회": "국토교통위원회\n윤리특별위원회\n예산결산특별위원회",
  "id": "1125",
  "주요경력": "명지대학교 대학원 정치외교학과 박사과정 수료",
  "본회의_출석률_등수": 281,
  "재산등수": 123,
  "상임위원회_출석률": [
    {
      "위원회": "국토교통위원회",
      "출석률": 90.63,
      "등수": 16,
      "총원": 29
    },
    {
      "위원회": "예산결산특별위원회",
      "출석률": 78.95,
      "등수": 47,
      "총원": 50
    },
    {
      "위원회": "윤리특별위원회",
      "출석률": 100,
      "등수": 1,
      "총원": 11
    }
  ],
  "이름": "엄태영",
  "정당": "국민의힘",
  "위원회별_발의법안": [
    {
      "발의수": 12,
      "위원회": "국토교통위원회"
    },
    {
      "발의수": 10,
      "위원회": "행정안전위원회"
    },
    {
      "발의수": 6,
      "위원회": "국회운영위원회"
    },
    {
      "발의수": 6,
      "위원회": "보건복지위원회"
    },
    {
      "발의수": 5,
      "위원회": "환경노동위원회"
    },
    {
      "발의수": 4,
      "위원회": "법제사법위원회"
    },
    {
      "발의수": 4,
      "위원회": "정무위원회"
    },
    {
      "발의수": 3,
      "위원회": "농림축산식품해양수산위원회"
    },
    {
      "발의수": 3,
      "위원회": "산업통상자원중소벤처기업위원회"
    },
    {
      "발의수": 2,
      "위원회": "기획재정위원회"
    },
    {
      "발의수": 2,
      "위원회": "문화체육관광위원회"
    },
    {
      "발의수": 1,
      "위원회": ""
    },
    {
      "발의수": 1,
      "위원회": "외교통일위원회"
    }
  ],
  "대표발의법안_등수": 196,
  "연도별_재산": [
    {
      "연도": 2020,
      "재산": 657972
    },
    {
      "연도": 2021,
      "재산": 692704
    },
    {
      "연도": 2022,
      "재산": 875015
    }
  ],
  "대표발의법안": 59
}
