{
  "연락처": "의원회관 504호 | 전화 02-784-4570 | 팩스 02-6788-6340",
  "당선횟수": 4,
  "본회의_출석률": 95.81,
  "소속위원회": "기획재정위원회\n정보위원회",
  "id": "359",
  "주요경력": "경희대학교 행정대학원 졸업(행정학석사)",
  "본회의_출석률_등수": 8,
  "재산등수": 222,
  "상임위원회_출석률": [
    {
      "위원회": "기획재정위원회",
      "출석률": 87.5,
      "등수": 24,
      "총원": 26
    },
    {
      "위원회": "정보위원회",
      "출석률": 73.91,
      "등수": 9,
      "총원": 11
    }
  ],
  "이름": "김태년",
  "정당": "더불어민주당",
  "위원회별_발의법안": [
    {
      "발의수": 7,
      "위원회": "기획재정위원회"
    },
    {
      "발의수": 5,
      "위원회": "환경노동위원회"
    },
    {
      "발의수": 4,
      "위원회": "보건복지위원회"
    },
    {
      "발의수": 2,
      "위원회": "국토교통위원회"
    },
    {
      "발의수": 2,
      "위원회": "국회운영위원회"
    },
    {
      "발의수": 2,
      "위원회": "산업통상자원중소벤처기업위원회"
    },
    {
      "발의수": 1,
      "위원회": "정치개혁 특별위원회"
    },
    {
      "발의수": 1,
      "위원회": "행정안전위원회"
    },
    {
      "발의수": 1,
      "위원회": "법제사법위원회"
    },
    {
      "발의수": 1,
      "위원회": "과학기술정보방송통신위원회"
    },
    {
      "발의수": 1,
      "위원회": "여성가족위원회"
    },
    {
      "발의수": 1,
      "위원회": "정치개혁특별위원회"
    }
  ],
  "대표발의법안_등수": 113,
  "연도별_재산": [
    {
      "연도": 2020,
      "재산": 820212
    },
    {
      "연도": 2021,
      "재산": 887789
    },
    {
      "연도": 2022,
      "재산": 956764
    }
  ],
  "대표발의법안": 28
}
