{
  "id": "2112002-2",
  "regionId": "2112002",
  "imageUrl": "https://s3.whitekiwi.link/vote-for.kr/data/images/candidates/2112002-2.jpg",
  "기호": 2,
  "이름": "나경원",
  "생년월일": "19631206",
  "정당": "국민의힘",
  "성별": "여",
  "직업": "정당인",
  "학력": "서울대학교 대학원 법학과 박사과정 수료",
  "경력": "(전)4선 국회의원(제17,18,19,20대)\n(전)자유한국당 원내대표",
  "재산": 5831584,
  "군필여부": false,
  "전과건수": 0,
  "news": [
    {
      "date": "Tue, 09 Apr 2024 20:12:00 +0900",
      "title": "[돌비뉴스] 나경원 입에서 나온 \"지국비조\"…국민의미래는 어쩌고?",
      "link": "https://n.news.naver.com/mnews/article/437/0000387767?sid=165"
    },
    {
      "date": "Tue, 09 Apr 2024 19:28:00 +0900",
      "title": "[더스팟 254]한강벨트 최전선…‘경찰 출신’ 류삼영 vs ‘4선 중진’ 나경원",
      "link": "https://n.news.naver.com/mnews/article/449/0000272178?sid=100"
    },
    {
      "date": "Tue, 09 Apr 2024 19:14:00 +0900",
      "title": "나경원 \"정부 조금 부족...야당 오만함 봐야\"",
      "link": "https://www.ajunews.com/view/20240409190726205"
    },
    {
      "date": "Tue, 09 Apr 2024 19:13:00 +0900",
      "title": "나경원 “저점 찍고 올라가…맘카페서 지국비조 유행어”",
      "link": "https://n.news.naver.com/mnews/article/021/0002631317?sid=165"
    },
    {
      "date": "Tue, 09 Apr 2024 19:05:00 +0900",
      "title": "나경원, 조국혁신당 언급 “‘지국비조’가 유행어”",
      "link": "https://n.news.naver.com/mnews/article/449/0000272168?sid=115"
    },
    {
      "date": "Tue, 09 Apr 2024 18:10:00 +0900",
      "title": "[포토] 지지 호소하는 나경원 후보",
      "link": "https://www.newscj.com/news/articleView.html?idxno=3128005"
    },
    {
      "date": "Tue, 09 Apr 2024 18:10:00 +0900",
      "title": "[포토] 지지 호소하는 나경원",
      "link": "https://www.newscj.com/news/articleView.html?idxno=3128007"
    },
    {
      "date": "Tue, 09 Apr 2024 18:08:00 +0900",
      "title": "[포토] 한동훈 위원장, 장진영-나경원 후보 지지 호소",
      "link": "https://www.newscj.com/news/articleView.html?idxno=3128002"
    },
    {
      "date": "Tue, 09 Apr 2024 18:06:00 +0900",
      "title": "[포토] 한동훈 위원장, 기호 2번 장진영-나경원 후보 지지 호소",
      "link": "https://www.newscj.com/news/articleView.html?idxno=3128001"
    },
    {
      "date": "Tue, 09 Apr 2024 18:06:00 +0900",
      "title": "[포토] 한동훈 위원장, 기호 2번 장진영-나경원 지지 호소",
      "link": "https://www.newscj.com/news/articleView.html?idxno=3127999"
    },
    {
      "date": "Tue, 09 Apr 2024 18:04:00 +0900",
      "title": "[포토] 장진영-나경원 지원 호소하는 한동훈 비대위원장",
      "link": "https://www.newscj.com/news/articleView.html?idxno=3127995"
    },
    {
      "date": "Tue, 09 Apr 2024 18:04:00 +0900",
      "title": "[포토] 장진영-나경원 지원 호소하는 한동훈 위원장",
      "link": "https://www.newscj.com/news/articleView.html?idxno=3127997"
    },
    {
      "date": "Tue, 09 Apr 2024 18:01:00 +0900",
      "title": "초경합 동작을 나경원 \"정부가 좀 부족, 야당 오만함 봐야\"",
      "link": "https://n.news.naver.com/mnews/article/053/0000042771?sid=100"
    },
    {
      "date": "Tue, 09 Apr 2024 18:00:00 +0900",
      "title": "“최소한의 균형?” 나경원 입에서 “지국비조” 나왔다",
      "link": "https://n.news.naver.com/mnews/article/022/0003922694?sid=100"
    },
    {
      "date": "Tue, 09 Apr 2024 18:00:00 +0900",
      "title": "민주 류삼영 \"나경원은 윤 정권 아바타…싸워 이길 것\"",
      "link": "https://n.news.naver.com/mnews/article/003/0012482297?sid=165"
    },
    {
      "date": "Tue, 09 Apr 2024 17:53:00 +0900",
      "title": "원희룡 안철수 나경원 추미애 이광재…승패에 달린 잠룡들의 운명",
      "link": "https://n.news.naver.com/mnews/article/421/0007470153?sid=165"
    },
    {
      "date": "Tue, 09 Apr 2024 17:50:00 +0900",
      "title": "[22대 총선] 나경원 “지국비조 유행...반성할 건 반성하겠다”",
      "link": "https://www.smartfn.co.kr/article/view/sfn202404090064"
    },
    {
      "date": "Tue, 09 Apr 2024 17:44:00 +0900",
      "title": "[총선 D-1] 與, 서울 15곳 총력 유세…\"한 표 때문에 후회 말자\"(종합)",
      "link": "https://n.news.naver.com/mnews/article/001/0014621128?sid=100"
    },
    {
      "date": "Tue, 09 Apr 2024 17:42:00 +0900",
      "title": "\"단 1%에 당락 갈린다\" 수도권 26~31곳 초박빙 접전지역 보니",
      "link": "https://n.news.naver.com/mnews/article/011/0004325676?sid=165"
    },
    {
      "date": "Tue, 09 Apr 2024 17:39:00 +0900",
      "title": "'최대 격전지' 동작 방문한 한동훈 \"野 200석 막아달라\"",
      "link": "https://n.news.naver.com/mnews/article/629/0000279838?sid=165"
    }
  ],
  "연도별_재산": [
    {
      "연도": 2023,
      "재산": 5831584
    }
  ],
  "huboid": "100152037",
  "전과ImgUrl": "https://s3.whitekiwi.link/vote-for.kr/data/images/jeon-gwa/2112002-2.jpg",
  "공보PdfUrl": "https://s3.whitekiwi.link/vote-for.kr/공보/2112002-2.pdf",
  "공보ImgUrls": [
    "https://s3.whitekiwi.link/vote-for.kr/공보/images/2112002-2-0.jpg",
    "https://s3.whitekiwi.link/vote-for.kr/공보/images/2112002-2-1.jpg",
    "https://s3.whitekiwi.link/vote-for.kr/공보/images/2112002-2-10.jpg",
    "https://s3.whitekiwi.link/vote-for.kr/공보/images/2112002-2-11.jpg",
    "https://s3.whitekiwi.link/vote-for.kr/공보/images/2112002-2-2.jpg",
    "https://s3.whitekiwi.link/vote-for.kr/공보/images/2112002-2-3.jpg",
    "https://s3.whitekiwi.link/vote-for.kr/공보/images/2112002-2-4.jpg",
    "https://s3.whitekiwi.link/vote-for.kr/공보/images/2112002-2-5.jpg",
    "https://s3.whitekiwi.link/vote-for.kr/공보/images/2112002-2-6.jpg",
    "https://s3.whitekiwi.link/vote-for.kr/공보/images/2112002-2-7.jpg",
    "https://s3.whitekiwi.link/vote-for.kr/공보/images/2112002-2-8.jpg",
    "https://s3.whitekiwi.link/vote-for.kr/공보/images/2112002-2-9.jpg"
  ]
}
