{
  "id": "2260902-7",
  "regionId": "2260902",
  "imageUrl": "https://s3.whitekiwi.link/vote-for.kr/data/images/candidates/2260902-7.jpg",
  "기호": 7,
  "이름": "박주언",
  "생년월일": "19781101",
  "정당": "무소속",
  "성별": "남",
  "직업": "의사",
  "학력": "부산대학교 의학과 졸업",
  "경력": "(현)민중의의원 대표\n(현)노숙인 진료시설 운영",
  "재산": 728444,
  "군필여부": true,
  "전과건수": 0,
  "news": [
    {
      "date": "Mon, 01 Apr 2024 16:34:00 +0900",
      "title": "[4.10총선-176] 부산 해운대갑, 홍순헌vs주진우vs박주언. 보수아성 무너지나",
      "link": "http://www.mhj21.com/160224"
    },
    {
      "date": "Fri, 29 Mar 2024 16:24:00 +0900",
      "title": "[나는 후보자다] 해운대구갑 기호 7번 박주언 후보",
      "link": "http://news.lghellovision.net/news/articleView.html?idxno=461490"
    },
    {
      "date": "Mon, 15 Jan 2024 18:12:00 +0900",
      "title": "부산 제22대 국회의원 선거 예비 후보자(1월 15일 18시 기준)",
      "link": "http://news.lghellovision.net/news/articleView.html?idxno=451921"
    },
    {
      "date": "Mon, 15 Jan 2024 13:04:00 +0900",
      "title": "[선거 레이더] 하태경 떠나는 해운대갑…\"보수 텃밭 사수\" vs. \"정권 교체 할...",
      "link": "http://news.lghellovision.net/news/articleView.html?idxno=451788"
    },
    {
      "date": "Fri, 12 Jan 2024 13:22:00 +0900",
      "title": "부산 제22대 국회의원선거 예비 후보자(12일 오후1시 기준)",
      "link": "http://news.lghellovision.net/news/articleView.html?idxno=451620"
    },
    {
      "date": "Thu, 02 Jun 2022 23:52:00 +0900",
      "title": "광역의원 당선인 명단",
      "link": "http://www.gnmaeil.com/news/articleView.html?idxno=496750"
    },
    {
      "date": "Thu, 02 Jun 2022 23:34:00 +0900",
      "title": "6.1 지방선거 광역의원(비례) 당선인",
      "link": "http://www.gnnews.co.kr/news/articleView.html?idxno=502123"
    },
    {
      "date": "Thu, 02 Jun 2022 19:03:00 +0900",
      "title": "부울경 광역의원 지역구 당선인 최종 득표",
      "link": "https://n.news.naver.com/mnews/article/658/0000011258?sid=100"
    },
    {
      "date": "Thu, 02 Jun 2022 15:03:00 +0900",
      "title": "[제8회 지방선거·국회의원 보선] 경남 당선자 명단",
      "link": "https://n.news.naver.com/mnews/article/003/0011226086?sid=102"
    },
    {
      "date": "Thu, 02 Jun 2022 13:53:00 +0900",
      "title": "[광역의원 당선인 명단] 경남",
      "link": "https://n.news.naver.com/mnews/article/421/0006135723?sid=100"
    },
    {
      "date": "Thu, 02 Jun 2022 13:40:00 +0900",
      "title": "[광역의원 당선인 명단] 경남",
      "link": "https://www.jeonmae.co.kr/news/articleView.html?idxno=893442"
    },
    {
      "date": "Thu, 02 Jun 2022 10:19:00 +0900",
      "title": "[광역의원 당선인 명단] 경남",
      "link": "https://n.news.naver.com/mnews/article/001/0013222145?sid=100"
    },
    {
      "date": "Thu, 02 Jun 2022 09:56:00 +0900",
      "title": "6.1 지선 구인모 거창군수 후보 재선 성공",
      "link": "http://www.breaknews.com/899358"
    },
    {
      "date": "Wed, 25 May 2022 17:07:00 +0900",
      "title": "[경남] 일본군 위안부 역사관 건립에 확약한 후보는?",
      "link": "https://n.news.naver.com/mnews/article/047/0002354445?sid=102"
    },
    {
      "date": "Sun, 15 May 2022 17:44:00 +0900",
      "title": "6.1 지방선거 출마자 - 경남도의원",
      "link": "http://www.gndomin.com/news/articleView.html?idxno=315030"
    },
    {
      "date": "Sat, 14 May 2022 21:40:00 +0900",
      "title": "[8회 지방선거] 경남 광역의원 후보 재산, 병역, 납세 실적 및 전과 유무",
      "link": "http://www.topstarnews.net/news/articleView.html?idxno=14692048"
    },
    {
      "date": "Fri, 13 May 2022 23:11:00 +0900",
      "title": "[광역의원 후보 명단] 경남",
      "link": "https://n.news.naver.com/mnews/article/001/0013177927?sid=100"
    },
    {
      "date": "Sun, 08 May 2022 18:28:00 +0900",
      "title": "국민의힘 지방선거 경남 기초단체장 마지막 퍼즐 완성",
      "link": "http://www.newsgn.com/327561"
    },
    {
      "date": "Fri, 22 May 2020 17:10:00 +0900",
      "title": "4.15 총선 선거비용 공개…부산 지역 후보자들은 얼마 썼나",
      "link": "http://www.kookje.co.kr/news2011/asp/newsbody.asp?code=0100&key=20200522.99099007113"
    },
    {
      "date": "Mon, 20 Apr 2020 00:06:00 +0900",
      "title": "국회 게임포럼 의원, 절반 생존…21대 국회, 게임 '대변자' 줄어",
      "link": "http://www.newsworks.co.kr/news/articleView.html?idxno=449127"
    }
  ],
  "연도별_재산": [
    {
      "연도": 2023,
      "재산": 728444
    }
  ],
  "huboid": "100152108",
  "전과ImgUrl": "https://s3.whitekiwi.link/vote-for.kr/data/images/jeon-gwa/2260902-7.jpg",
  "공보PdfUrl": "https://s3.whitekiwi.link/vote-for.kr/공보/2260902-7.pdf",
  "공보ImgUrls": [
    "https://s3.whitekiwi.link/vote-for.kr/공보/images/2260902-7-0.jpg",
    "https://s3.whitekiwi.link/vote-for.kr/공보/images/2260902-7-1.jpg",
    "https://s3.whitekiwi.link/vote-for.kr/공보/images/2260902-7-10.jpg",
    "https://s3.whitekiwi.link/vote-for.kr/공보/images/2260902-7-11.jpg",
    "https://s3.whitekiwi.link/vote-for.kr/공보/images/2260902-7-2.jpg",
    "https://s3.whitekiwi.link/vote-for.kr/공보/images/2260902-7-3.jpg",
    "https://s3.whitekiwi.link/vote-for.kr/공보/images/2260902-7-4.jpg",
    "https://s3.whitekiwi.link/vote-for.kr/공보/images/2260902-7-5.jpg",
    "https://s3.whitekiwi.link/vote-for.kr/공보/images/2260902-7-6.jpg",
    "https://s3.whitekiwi.link/vote-for.kr/공보/images/2260902-7-7.jpg",
    "https://s3.whitekiwi.link/vote-for.kr/공보/images/2260902-7-8.jpg",
    "https://s3.whitekiwi.link/vote-for.kr/공보/images/2260902-7-9.jpg"
  ]
}
