{
  "전과건수": 0,
  "imageUrl": "https://s3.whitekiwi.link/vote-for.kr/data/images/candidates/2414902-2.jpg",
  "id": "2414902-2",
  "재산": 3490357,
  "생년월일": "19610617",
  "경력": "(현) 제21대 국회의원\n(전) 제15대 통계청장",
  "학력": "미국 코넬대학교 노동경제학과 (경제학박사) (1991.8.~1995.8.)",
  "직업": "국회의원",
  "성별": "남",
  "id_21th": "1057",
  "regionId": "2414902",
  "기호": 2,
  "군필여부": true,
  "news": [
    {
      "date": "Sun, 07 Apr 2024 21:20:00 +0900",
      "title": "[유세장 직격 인터뷰] 유승민·김부겸·김선교·이재강·유경준",
      "link": "https://www.joongboo.com/news/articleView.html?idxno=363645925"
    },
    {
      "date": "Sun, 07 Apr 2024 15:38:00 +0900",
      "title": "유경준 의원, 동탄·반월 지역 '365일 편리한 교육인프라 조성' 공약 발표",
      "link": "https://www.thefairnews.co.kr/news/articleView.html?idxno=25302"
    },
    {
      "date": "Fri, 05 Apr 2024 16:18:00 +0900",
      "title": "유경준 후보 \"화성시 지방세 49.1%, 동탄·반월서 나온다\"",
      "link": "http://www.shinailbo.co.kr/news/articleView.html?idxno=1854564"
    },
    {
      "date": "Fri, 05 Apr 2024 11:20:00 +0900",
      "title": "유경준 후보 \"지방소득세, 58.2% 동탄, 반월에서\"...\"野, 세수 부족 지적 팩트...",
      "link": "http://www.fntoday.co.kr/news/articleView.html?idxno=317799"
    },
    {
      "date": "Thu, 04 Apr 2024 20:11:00 +0900",
      "title": "화성정 유경준 “동탄시 독립으로 ‘교통·교육 천국’ 만들겠다” [이런정치...",
      "link": "https://n.news.naver.com/mnews/article/016/0002290895?sid=100"
    },
    {
      "date": "Thu, 04 Apr 2024 17:44:00 +0900",
      "title": "유경준 의원, 11호 공약으로 '삼성 화성캠퍼스 주차타워 증축 지원' 발표",
      "link": "https://www.thefairnews.co.kr/news/articleView.html?idxno=25185"
    },
    {
      "date": "Thu, 04 Apr 2024 09:32:00 +0900",
      "title": "유경준 \"이원욱과 단일화? 대화해볼 것...내가 사퇴할 일은 없다\"",
      "link": "https://news.bbsi.co.kr/news/articleView.html?idxno=3151125"
    },
    {
      "date": "Wed, 03 Apr 2024 14:42:00 +0900",
      "title": "[총선 D-7] 국민의힘 유경준 화성정 후보 '삼성 화성캠퍼스 주차타워 증축 지...",
      "link": "https://www.jeonmae.co.kr/news/articleView.html?idxno=1026815"
    },
    {
      "date": "Wed, 03 Apr 2024 12:18:00 +0900",
      "title": "유경준 후보, 삼성 화성캠퍼스 주차타워 증축 지원 약속",
      "link": "https://gg.newdaily.co.kr/site/data/html/2024/04/03/2024040300115.html"
    },
    {
      "date": "Tue, 02 Apr 2024 19:15:00 +0900",
      "title": "경기 화성정 국힘 유경준 'GTX-C노선 동탄 연장' 공약",
      "link": "https://n.news.naver.com/mnews/article/003/0012467257?sid=102"
    },
    {
      "date": "Tue, 02 Apr 2024 14:40:00 +0900",
      "title": "[4·10 총선 인터뷰] 유경준 \"동탄과 반월의 ‘잃어버린 15년’ 되찾을 것\"",
      "link": "https://gg.newdaily.co.kr/site/data/html/2024/04/02/2024040200172.html"
    },
    {
      "date": "Tue, 02 Apr 2024 13:08:00 +0900",
      "title": "유경준 후보, 제10호 공약으로 ‘솔빛나루역 신설과 GTX-C 2 동탄 연장’ 약속",
      "link": "http://www.shinailbo.co.kr/news/articleView.html?idxno=1852361"
    },
    {
      "date": "Tue, 02 Apr 2024 10:26:00 +0900",
      "title": "국민의힘 유경준 후보, \"철도전문가 유경준, GTX-C 2동탄까지 잇는다\"",
      "link": "http://www.fntoday.co.kr/news/articleView.html?idxno=317443"
    },
    {
      "date": "Mon, 01 Apr 2024 20:13:00 +0900",
      "title": "[경기 화성정] 민주당 전용기 53.3%, 국민의힘 유경준 30.5%, 개혁신당 이원욱...",
      "link": "https://n.news.naver.com/mnews/article/047/0002428441?sid=165"
    },
    {
      "date": "Mon, 01 Apr 2024 18:10:00 +0900",
      "title": "[여론조사 꽃 총선/경기 화성정] 野 전용기, 與 전략공천 유경준에 29%p 차 우...",
      "link": "http://www.goodmorningcc.com/news/articleView.html?idxno=307376"
    },
    {
      "date": "Mon, 01 Apr 2024 16:43:00 +0900",
      "title": "경기 화성정, 전용기 45.7%·유경준 16.7%·이원욱 8.8% [여론조사꽃]",
      "link": "https://n.news.naver.com/mnews/article/123/0002331014?sid=100"
    },
    {
      "date": "Mon, 01 Apr 2024 16:16:00 +0900",
      "title": "국민의힘 '경제통' 유경준이 \"동탄 독립\" 외치는 이유",
      "link": "https://n.news.naver.com/mnews/article/079/0003880529?sid=165"
    },
    {
      "date": "Mon, 01 Apr 2024 15:36:00 +0900",
      "title": "총선 국면 역할 늘리는 유승민···차기 당권 겨냥하나",
      "link": "http://www.m-i.kr/news/articleView.html?idxno=1107152"
    },
    {
      "date": "Mon, 01 Apr 2024 14:18:00 +0900",
      "title": "[총선 D-9] 국민의힘 유경준 경기 화성정 후보, 총선 9호 공약 '동탄시, 신기...",
      "link": "https://www.jeonmae.co.kr/news/articleView.html?idxno=1025954"
    },
    {
      "date": "Mon, 01 Apr 2024 14:04:00 +0900",
      "title": "화성정 국힘 유경준 “동탄시, 신기술 테스트베드 구축”",
      "link": "https://n.news.naver.com/mnews/article/421/0007450253?sid=102"
    }
  ],
  "정당": "국민의힘",
  "이름": "유경준",
  "연도별_재산": [
    {
      "연도": 2020,
      "재산": 2688409
    },
    {
      "연도": 2021,
      "재산": 2964538
    },
    {
      "연도": 2022,
      "재산": 3337088
    },
    {
      "연도": 2023,
      "재산": 3490357
    }
  ],
  "huboid": "100153015",
  "전과ImgUrl": "https://s3.whitekiwi.link/vote-for.kr/data/images/jeon-gwa/2414902-2.jpg",
  "공보PdfUrl": "https://s3.whitekiwi.link/vote-for.kr/공보/2414902-2.pdf",
  "21th": {
    "연락처": "의원회관 434호 | 전화 02-784-2051 | 팩스 02-6788-6800",
    "당선횟수": 1,
    "본회의_출석률": 86.83,
    "소속위원회": "국회부산세계박람회유치지원특별위원회\n국토교통위원회\n인구위기특별위원회\n연금개혁특별위원회",
    "id": "1057",
    "주요경력": "미국 코넬대학교 노동경제학과(경제학박사)(1991.8~1995.8)",
    "본회의_출석률_등수": 241,
    "재산등수": 53,
    "상임위원회_출석률": [
      {
        "위원회": "국토교통위원회",
        "출석률": 94,
        "등수": 15,
        "총원": 29
      },
      {
        "위원회": "국회 2030 부산세계박람회 유치지원 특별위원회",
        "출석률": 92.86,
        "등수": 2,
        "총원": 18
      },
      {
        "위원회": "연금개혁특별위원회",
        "출석률": 100,
        "등수": 1,
        "총원": 15
      },
      {
        "위원회": "인구위기특별위원회",
        "출석률": 66.67,
        "등수": 15,
        "총원": 17
      }
    ],
    "이름": "유경준",
    "정당": "국민의힘",
    "위원회별_발의법안": [
      {
        "발의수": 25,
        "위원회": "국토교통위원회"
      },
      {
        "발의수": 22,
        "위원회": "기획재정위원회"
      },
      {
        "발의수": 8,
        "위원회": "행정안전위원회"
      },
      {
        "발의수": 2,
        "위원회": "환경노동위원회"
      },
      {
        "발의수": 2,
        "위원회": "보건복지위원회"
      },
      {
        "발의수": 2,
        "위원회": "법제사법위원회"
      },
      {
        "발의수": 2,
        "위원회": "국방위원회"
      },
      {
        "발의수": 1,
        "위원회": "문화체육관광위원회"
      },
      {
        "발의수": 1,
        "위원회": "산업통상자원중소벤처기업위원회"
      },
      {
        "발의수": 1,
        "위원회": "민생경제안정특별위원회"
      },
      {
        "발의수": 1,
        "위원회": "과학기술정보방송통신위원회"
      }
    ],
    "대표발의법안_등수": 168,
    "연도별_재산": [
      {
        "연도": 2020,
        "재산": 2688409
      },
      {
        "연도": 2021,
        "재산": 2964538
      },
      {
        "연도": 2022,
        "재산": 3337088
      }
    ],
    "대표발의법안": 67,
    "주요법안표결": [
      {
        "별칭": "전세사기피해자 지원 특별법",
        "의안명": "전세사기피해자 지원 및 주거안정에 관한 특별법안(대안)(국토교통위원장)",
        "의안번호": 2122268,
        "찬반여부": "찬성"
      },
      {
        "별칭": "임대차 보호법",
        "의안명": "주택임대차보호법 일부개정법률안(대안)(법제사법위원장)",
        "의안번호": 2102500,
        "찬반여부": "불참"
      },
      {
        "별칭": "간호법",
        "의안명": "간호법안(대안)",
        "의안번호": 2120877,
        "찬반여부": "불참"
      },
      {
        "별칭": "중대재해법",
        "의안명": "중대재해 처벌 등에 관한 법률안(대안)(법제사법위원장)",
        "의안번호": 2107249,
        "찬반여부": "반대"
      },
      {
        "별칭": "이태원 참사 특별법",
        "의안명": "10·29이태원참사 피해자 권리보장과 진상규명 및 재발방지를 위한 특별법안",
        "의안번호": 2121515,
        "찬반여부": "불참"
      },
      {
        "별칭": "노란봉투법",
        "의안명": "노동조합 및 노동관계조정법 일부개정법률안(대안)(환경노동위원장)",
        "의안번호": 2123038,
        "찬반여부": "불참"
      },
      {
        "별칭": "학자금 무이자 대출",
        "의안명": "취업 후 학자금 상환 특별법 일부개정법률안(교육위원장)",
        "의안번호": 2125809,
        "찬반여부": "찬성"
      },
      {
        "별칭": "양곡관리법",
        "의안명": "양곡관리법 일부개정법률안(대안)(김성환의원 외 30인)",
        "의안번호": 2119727,
        "찬반여부": "반대"
      },
      {
        "별칭": "개망신법",
        "의안명": "신용정보의 이용 및 보호에 관한 법률 일부개정법률안",
        "의안번호": 2119142,
        "찬반여부": "찬성"
      },
      {
        "별칭": "개망신법",
        "의안명": "정보통신망 이용촉진 및 정보보호 등에 관한 법률 일부개정법률안(대안)(과학기술정보방송통신위원장)",
        "의안번호": 2126369,
        "찬반여부": "찬성"
      },
      {
        "별칭": "1기 신도시 특별법",
        "의안명": "노후계획도시 정비 및 지원에 관한 특별법안(대안)(국토교통위원장)",
        "의안번호": 2125837,
        "찬반여부": "찬성"
      },
      {
        "별칭": "신공항 특별법",
        "의안명": "가덕도신공항 건설을 위한 특별법 일부개정법률안(대안)(국토교통위원장)",
        "의안번호": 2120933,
        "찬반여부": "찬성"
      }
    ],
    "워드클라우드": [
      {
        "단어": "수도",
        "count": "177"
      },
      {
        "단어": "소득",
        "count": "171"
      },
      {
        "단어": "공시가격",
        "count": "165"
      },
      {
        "단어": "종부세",
        "count": "120"
      },
      {
        "단어": "국세청",
        "count": "112"
      },
      {
        "단어": "한국은행",
        "count": "112"
      },
      {
        "단어": "서울",
        "count": "107"
      },
      {
        "단어": "한국",
        "count": "102"
      },
      {
        "단어": "통계청",
        "count": "101"
      },
      {
        "단어": "국가",
        "count": "96"
      }
    ],
    "대표법안목록": [
      {
        "제안일": "2024-02-29",
        "의안명": "빈집 및 소규모주택 정비에 관한 특례법 일부개정법률안(유경준의원 등 10인) ",
        "발의자": "유경준",
        "상임위원회": "국토교통위원회",
        "진행상황": ""
      },
      {
        "제안일": "2024-02-29",
        "의안명": "도시 및 주거환경정비법 일부개정법률안(유경준의원 등 10인) ",
        "발의자": "유경준",
        "상임위원회": "국토교통위원회",
        "진행상황": ""
      },
      {
        "제안일": "2024-02-29",
        "의안명": "주택법 일부개정법률안(유경준의원 등 10인) ",
        "발의자": "유경준",
        "상임위원회": "국토교통위원회",
        "진행상황": ""
      },
      {
        "제안일": "2023-12-29",
        "의안명": "공휴일에 관한 법률 일부개정법률안(유경준의원 등 10인) ",
        "발의자": "유경준",
        "상임위원회": "행정안전위원회",
        "진행상황": ""
      },
      {
        "제안일": "2023-12-13",
        "의안명": "국민체육진흥법 일부개정법률안(유경준의원 등 14인) ",
        "발의자": "유경준",
        "상임위원회": "문화체육관광위원회",
        "진행상황": ""
      },
      {
        "제안일": "2023-11-30",
        "의안명": "특정건축물 정리에 관한 특별조치법안(유경준의원 등 10인) ",
        "발의자": "유경준",
        "상임위원회": "국토교통위원회",
        "진행상황": ""
      },
      {
        "제안일": "2023-11-27",
        "의안명": "특정건축물 정리에 관한 특별조치법안(유경준의원 등 10인) ",
        "발의자": "유경준",
        "상임위원회": "국토교통위원회",
        "진행상황": "철회"
      },
      {
        "제안일": "2023-11-20",
        "의안명": "고용정책 기본법 일부개정법률안(유경준의원 등 10인) ",
        "발의자": "유경준",
        "상임위원회": "환경노동위원회",
        "진행상황": ""
      },
      {
        "제안일": "2023-06-13",
        "의안명": "선거관리위원회법 일부개정법률안(유경준의원 등 12인) ",
        "발의자": "유경준",
        "상임위원회": "행정안전위원회",
        "진행상황": ""
      },
      {
        "제안일": "2023-05-31",
        "의안명": "주택법 일부개정법률안(유경준의원 등 12인) ",
        "발의자": "유경준",
        "상임위원회": "국토교통위원회",
        "진행상황": ""
      }
    ],
    "공약이행률": {
      "총공약수": 7,
      "공약이행수": 5
    },
    "공약이행률등수": 42,
    "공약이행수등수": 183
  },
  "공보ImgUrls": [
    "https://s3.whitekiwi.link/vote-for.kr/공보/images/2414902-2-0.jpg",
    "https://s3.whitekiwi.link/vote-for.kr/공보/images/2414902-2-1.jpg",
    "https://s3.whitekiwi.link/vote-for.kr/공보/images/2414902-2-10.jpg",
    "https://s3.whitekiwi.link/vote-for.kr/공보/images/2414902-2-11.jpg",
    "https://s3.whitekiwi.link/vote-for.kr/공보/images/2414902-2-2.jpg",
    "https://s3.whitekiwi.link/vote-for.kr/공보/images/2414902-2-3.jpg",
    "https://s3.whitekiwi.link/vote-for.kr/공보/images/2414902-2-4.jpg",
    "https://s3.whitekiwi.link/vote-for.kr/공보/images/2414902-2-5.jpg",
    "https://s3.whitekiwi.link/vote-for.kr/공보/images/2414902-2-6.jpg",
    "https://s3.whitekiwi.link/vote-for.kr/공보/images/2414902-2-7.jpg",
    "https://s3.whitekiwi.link/vote-for.kr/공보/images/2414902-2-8.jpg",
    "https://s3.whitekiwi.link/vote-for.kr/공보/images/2414902-2-9.jpg"
  ]
}
