{
  "전과건수": 0,
  "imageUrl": "https://raw.githubusercontent.com/WhiteKiwi/law-maker/main/data/images/candidates/2430401-2.jpg",
  "id": "2430401_2-2",
  "재산": 1112088,
  "생년월일": "19580122",
  "경력": "(전)민선3~4기 제천시장\n(현)제21대 국회의원",
  "학력": "명지대학교 대학원 정치외교학과 박사과정 수료",
  "직업": "국회의원",
  "성별": "남",
  "id_21th": "1125",
  "regionId": "2430401_2",
  "기호": 2,
  "군필여부": true,
  "news": [
    {
      "date": "Fri, 05 Apr 2024 14:54:00 +0900",
      "title": "국민의힘 제천·단양 엄태영 후보, 사전투표 첫날 압도적 지지 호소",
      "link": "https://www.gukjenews.com/news/articleView.html?idxno=2962319"
    },
    {
      "date": "Fri, 05 Apr 2024 06:15:00 +0900",
      "title": "총선 엿새 앞 '제천·단양 방송토론회'…야권 후보들 엄태영 협공",
      "link": "https://n.news.naver.com/mnews/article/421/0007460121?sid=165"
    },
    {
      "date": "Thu, 04 Apr 2024 20:39:00 +0900",
      "title": "[총선 D-6] 제천·단양 토론회 '후끈'…엄태영에 공격 집중",
      "link": "https://n.news.naver.com/mnews/article/001/0014611886?sid=165"
    },
    {
      "date": "Thu, 04 Apr 2024 19:28:00 +0900",
      "title": "[4·10 총선 인터뷰] 엄태영 국힘 제천단양 후보 \"지속가능한 도약의 발판 마...",
      "link": "https://www.cctoday.co.kr/news/articleView.html?idxno=2193920"
    },
    {
      "date": "Thu, 04 Apr 2024 18:28:00 +0900",
      "title": "국민의힘 제천·단양 엄태영 후보, 청년 소통 간담회 개최",
      "link": "https://www.gukjenews.com/news/articleView.html?idxno=2961617"
    }
  ],
  "정당": "국민의힘",
  "이름": "엄태영",
  "연도별_재산": [
    {
      "연도": 2020,
      "재산": 657972
    },
    {
      "연도": 2021,
      "재산": 692704
    },
    {
      "연도": 2022,
      "재산": 875015
    },
    {
      "연도": 2023,
      "재산": 1112088
    }
  ],
  "huboid": "100152754",
  "전과ImgUrl": "https://raw.githubusercontent.com/WhiteKiwi/law-maker/main/data/images/jeon-gwa/2430401-2.jpg",
  "공보PdfUrl": "https://s3.whitekiwi.link/vote-for.kr/공보/2430401_2-2.pdf"
}
