{
  "id": "2460403-8",
  "regionId": "2460403",
  "imageUrl": "https://s3.whitekiwi.link/vote-for.kr/data/images/candidates/2460403-8.jpg",
  "기호": 8,
  "이름": "신성식",
  "생년월일": "19651129",
  "정당": "무소속",
  "성별": "남",
  "직업": "정치인",
  "학력": "중앙대학교 법과대학 법학과 졸업",
  "경력": "(전)제42대 수원지방검찰청 검사장\n(전)대검찰청 반부패강력부장",
  "재산": 2736570,
  "군필여부": true,
  "전과건수": 0,
  "news": [
    {
      "date": "Tue, 09 Apr 2024 18:18:00 +0900",
      "title": "[4.10총선] 무소속 신성식, 당선하면 '민주당 입당'...윤 정부 조기 종식",
      "link": "https://www.polinews.co.kr/news/articleView.html?idxno=642805"
    },
    {
      "date": "Tue, 09 Apr 2024 05:20:00 +0900",
      "title": "[총선 D-1] 전남서 非민주당 국회의원 나올까…이정현·이석형·신성식 주목",
      "link": "https://n.news.naver.com/mnews/article/421/0007468142?sid=165"
    },
    {
      "date": "Sat, 06 Apr 2024 20:01:00 +0900",
      "title": "신성식 \"김문수 2억 상당 후원 받아, 정치자금법 위반\"",
      "link": "https://n.news.naver.com/mnews/article/079/0003882660?sid=165"
    },
    {
      "date": "Sat, 06 Apr 2024 16:10:00 +0900",
      "title": "순천 신성식 후보, 김문수 후보 허위사실 공표 등 고발",
      "link": "http://www.newskr.kr/news/articleView.html?idxno=94994"
    },
    {
      "date": "Sat, 06 Apr 2024 13:27:00 +0900",
      "title": "[4.10총선] 신성식, 김문수 최측근 비리 밝혀...사퇴 촉구",
      "link": "https://www.polinews.co.kr/news/articleView.html?idxno=642299"
    },
    {
      "date": "Fri, 05 Apr 2024 19:55:00 +0900",
      "title": "신성식, 민주당 김문수 '명예훼손, 모욕 혐의' 등 고발",
      "link": "https://n.news.naver.com/mnews/article/079/0003882549?sid=165"
    },
    {
      "date": "Fri, 05 Apr 2024 19:14:00 +0900",
      "title": "[4.10총선] 신성식 \"김문수 후보는 불법의 황제\" 반드시 벌 받아야",
      "link": "https://www.polinews.co.kr/news/articleView.html?idxno=642241"
    },
    {
      "date": "Fri, 05 Apr 2024 16:34:00 +0900",
      "title": "신성식 순천갑 무소속 후보 “김문수 민주당 후보 명예훼손 혐의 등 고발”",
      "link": "https://n.news.naver.com/mnews/article/016/0002291344?sid=100"
    },
    {
      "date": "Fri, 05 Apr 2024 15:36:00 +0900",
      "title": "[총선현장]신성식후보,허위사실과 명예훼손 등 김문수후보 고발",
      "link": "http://www.dailyimpact.co.kr/news/articleView.html?idxno=114343"
    },
    {
      "date": "Fri, 05 Apr 2024 15:20:00 +0900",
      "title": "순천 신성식 무소속 후보, “민주당 김문수 허위사실·모욕” 등 검찰 고발",
      "link": "https://ilyo.co.kr/?ac=article_view&entry_id=470142"
    },
    {
      "date": "Fri, 05 Apr 2024 14:30:00 +0900",
      "title": "무소속 신성식 \"김문수, 고가 차량 등 불법 후원받아\" 선관위 고발",
      "link": "https://www.straightnews.co.kr/news/articleView.html?idxno=247142"
    },
    {
      "date": "Fri, 05 Apr 2024 11:21:00 +0900",
      "title": "신성식 \"김문수, 재산신고 안된 차량·원룸 불법 후원받아\"",
      "link": "https://n.news.naver.com/mnews/article/421/0007461502?sid=165"
    },
    {
      "date": "Thu, 04 Apr 2024 17:56:00 +0900",
      "title": "[4.10총선]민주당 김문수, 정치자금법 위반 혐의...김형석 '사퇴주장'..신성식...",
      "link": "https://www.polinews.co.kr/news/articleView.html?idxno=642012"
    },
    {
      "date": "Thu, 04 Apr 2024 17:29:00 +0900",
      "title": "[4.10총선] 무소속 신성식 후보, 김문수 3종 의혹...선관위 고발",
      "link": "https://www.polinews.co.kr/news/articleView.html?idxno=642007"
    },
    {
      "date": "Thu, 04 Apr 2024 17:26:00 +0900",
      "title": "신성식 후보, 정치자금 3종 위반 \"김문수후보 의혹\"...선관위 고발",
      "link": "http://www.siminsori.com/news/articleView.html?idxno=261913"
    },
    {
      "date": "Thu, 04 Apr 2024 17:08:00 +0900",
      "title": "순천갑 신성식 후보, 민주당 김문수 후보 고발",
      "link": "http://news.lghellovision.net/news/articleView.html?idxno=462270"
    },
    {
      "date": "Thu, 04 Apr 2024 14:37:00 +0900",
      "title": "신성식 후보 “김문수 민주당 후보, 정치자금범 위반 의혹 밝혀라”",
      "link": "http://www.jnilbo.com/73233995702"
    },
    {
      "date": "Thu, 04 Apr 2024 14:21:00 +0900",
      "title": "순천 신성식 후보, 김문수 후보 정치자금법 위반 의혹 고발",
      "link": "https://n.news.naver.com/mnews/article/081/0003442046?sid=100"
    },
    {
      "date": "Thu, 04 Apr 2024 11:24:00 +0900",
      "title": "신성식 \"김문수 후보, '무상삼합' 의혹\" 고발장 접수",
      "link": "https://www.ajunews.com/view/20240404111225927"
    },
    {
      "date": "Wed, 03 Apr 2024 16:50:00 +0900",
      "title": "[전남 순천광양곡성구례갑] 더불어민주당 김문수 36.1%, 무소속 신성식 24.4%",
      "link": "https://n.news.naver.com/mnews/article/047/0002428808?sid=165"
    }
  ],
  "연도별_재산": [
    {
      "연도": 2023,
      "재산": 2736570
    }
  ],
  "huboid": "100152196",
  "전과ImgUrl": "https://s3.whitekiwi.link/vote-for.kr/data/images/jeon-gwa/2460403-8.jpg",
  "공보PdfUrl": "https://s3.whitekiwi.link/vote-for.kr/공보/2460403-8.pdf",
  "공보ImgUrls": [
    "https://s3.whitekiwi.link/vote-for.kr/공보/images/2460403-8-0.jpg",
    "https://s3.whitekiwi.link/vote-for.kr/공보/images/2460403-8-1.jpg",
    "https://s3.whitekiwi.link/vote-for.kr/공보/images/2460403-8-10.jpg",
    "https://s3.whitekiwi.link/vote-for.kr/공보/images/2460403-8-11.jpg",
    "https://s3.whitekiwi.link/vote-for.kr/공보/images/2460403-8-2.jpg",
    "https://s3.whitekiwi.link/vote-for.kr/공보/images/2460403-8-3.jpg",
    "https://s3.whitekiwi.link/vote-for.kr/공보/images/2460403-8-4.jpg",
    "https://s3.whitekiwi.link/vote-for.kr/공보/images/2460403-8-5.jpg",
    "https://s3.whitekiwi.link/vote-for.kr/공보/images/2460403-8-6.jpg",
    "https://s3.whitekiwi.link/vote-for.kr/공보/images/2460403-8-7.jpg",
    "https://s3.whitekiwi.link/vote-for.kr/공보/images/2460403-8-8.jpg",
    "https://s3.whitekiwi.link/vote-for.kr/공보/images/2460403-8-9.jpg"
  ]
}
